[
    {
      "id": 1,
      "question": "What type of website do you need?",
      "options": [
        { "type": "Business Website", "description": "A professional website for your business, including information about your services and products." },
        { "type": "E-commerce Website", "description": "An e-commerce website to sell products or services online." },
        { "type": "Portfolio Website", "description": "A website to showcase your work and projects, ideal for artists, designers, and photographers." },
        { "type": "Landing Page", "description": "A landing page to promote a specific product, service, or event." },
        { "type": "Other", "description": "" }
      ]
    }
]
  